{
	"title": "京成杯",
	"course": "コース:2,000メートル（芝・右）",
	"url": "https://www.jra.go.jp/datafile/seiseki/replay/2023/006.html",
	"horse": [
		{
			"rank": 1,
			"waku": "枠4青",
			"umaban": 4,
			"horse": "ソールオリエンス",
			"age": "牡3",
			"weight": "56.0",
			"jockey": "横山 武史",
			"time": "2:02.2",
			"margin": "",
			"h_weight": 462,
			"h_weight_zougen": 2,
			"f_time": "34.5",
			"trainer": "手塚 貴久",
			"pop": "2",
			"corner": [
				5,
				5,
				5,
				5
			]
		},
		{
			"rank": 2,
			"waku": "枠3赤",
			"umaban": 3,
			"horse": "オメガリッチマン",
			"age": "牡3",
			"weight": "56.0",
			"jockey": "石川 裕紀人",
			"time": "2:02.6",
			"margin": "２ 1/2",
			"h_weight": 434,
			"h_weight_zougen": -10,
			"f_time": "35.0",
			"trainer": "安田 翔伍",
			"pop": "9",
			"corner": [
				5,
				5,
				5,
				5
			]
		},
		{
			"rank": 3,
			"waku": "枠7橙",
			"umaban": 7,
			"horse": "セブンマジシャン",
			"age": "牡3",
			"weight": "56.0",
			"jockey": "C.ルメール",
			"time": "2:02.8",
			"margin": "１ 1/4",
			"h_weight": 480,
			"h_weight_zougen": -4,
			"f_time": "34.9",
			"trainer": "高野 友和",
			"pop": "1",
			"corner": [
				5,
				7,
				7,
				7
			]
		},
		{
			"rank": 4,
			"waku": "枠1白",
			"umaban": 1,
			"horse": "サヴォーナ",
			"age": "牡3",
			"weight": "56.0",
			"jockey": "田辺 裕信",
			"time": "2:02.9",
			"margin": "１／２",
			"h_weight": 520,
			"h_weight_zougen": 10,
			"f_time": "35.0",
			"trainer": "中竹 和也",
			"pop": "7",
			"corner": [
				8,
				7,
				7,
				7
			]
		},
		{
			"rank": 5,
			"waku": "枠5黄",
			"umaban": 5,
			"horse": "シルヴァーデューク",
			"age": "牡3",
			"weight": "56.0",
			"jockey": "T.バシュロ",
			"time": "2:03.0",
			"margin": "３／４",
			"h_weight": 470,
			"h_weight_zougen": 14,
			"f_time": "35.6",
			"trainer": "西村 真幸",
			"pop": "5",
			"corner": [
				4,
				3,
				3,
				3
			]
		},
		{
			"rank": 6,
			"waku": "枠8桃",
			"umaban": 9,
			"horse": "シャンパンカラー",
			"age": "牡3",
			"weight": "56.0",
			"jockey": "戸崎 圭太",
			"time": "2:03.0",
			"margin": "クビ",
			"h_weight": 502,
			"h_weight_zougen": 0,
			"f_time": "35.8",
			"trainer": "田中 剛",
			"pop": "3",
			"corner": [
				2,
				2,
				2,
				2
			]
		},
		{
			"rank": 7,
			"waku": "枠2黒",
			"umaban": 2,
			"horse": "シーウィザード",
			"age": "牡3",
			"weight": "56.0",
			"jockey": "三浦 皇成",
			"time": "2:03.1",
			"margin": "クビ",
			"h_weight": 474,
			"h_weight_zougen": 2,
			"f_time": "35.8",
			"trainer": "鹿戸 雄一",
			"pop": "4",
			"corner": [
				3,
				3,
				3,
				3
			]
		},
		{
			"rank": 8,
			"waku": "枠8桃",
			"umaban": 8,
			"horse": "グラニット",
			"age": "牡3",
			"weight": "56.0",
			"jockey": "嶋田 純次",
			"time": "2:03.3",
			"margin": "１ 1/4",
			"h_weight": 460,
			"h_weight_zougen": 8,
			"f_time": "36.5",
			"trainer": "大和田 成",
			"pop": "6",
			"corner": [
				1,
				1,
				1,
				1
			]
		},
		{
			"rank": 9,
			"waku": "枠6緑",
			"umaban": 6,
			"horse": "シルバースペード",
			"age": "牡3",
			"weight": "56.0",
			"jockey": "吉田 豊",
			"time": "2:03.4",
			"margin": "１／２",
			"h_weight": 474,
			"h_weight_zougen": 12,
			"f_time": "35.3",
			"trainer": "小野 次郎",
			"pop": "8",
			"corner": [
				8,
				9,
				9,
				9
			]
		}
	]
}