{
	"title": "報知杯弥生賞ディープインパクト記念",
	"course": "コース:2,000メートル（芝・右）",
	"url": "https://www.jra.go.jp/datafile/seiseki/replay/2024/024.html",
	"horse": [
		{
			"rank": 1,
			"waku": "枠6緑",
			"umaban": 7,
			"horse": "コスモキュランダ",
			"age": "牡3",
			"weight": "57.0",
			"jockey": "M.デムーロ",
			"time": "1:59.8",
			"margin": "",
			"h_weight": 504,
			"h_weight_zougen": 6,
			"f_time": "34.9",
			"trainer": "加藤 士津八",
			"pop": "6",
			"corner": [
				9,
				7,
				2,
				2
			]
		},
		{
			"rank": 2,
			"waku": "枠5黄",
			"umaban": 5,
			"horse": "シンエンペラー",
			"age": "牡3",
			"weight": "57.0",
			"jockey": "川田 将雅",
			"time": "2:00.0",
			"margin": "１ 1/4",
			"h_weight": 480,
			"h_weight_zougen": -2,
			"f_time": "34.8",
			"trainer": "矢作 芳人",
			"pop": "3",
			"corner": [
				4,
				3,
				5,
				5
			]
		},
		{
			"rank": 3,
			"waku": "枠7橙",
			"umaban": 8,
			"horse": "シリウスコルト",
			"age": "牡3",
			"weight": "57.0",
			"jockey": "三浦 皇成",
			"time": "2:00.2",
			"margin": "１ 1/4",
			"h_weight": 482,
			"h_weight_zougen": 2,
			"f_time": "35.5",
			"trainer": "宗像 義忠",
			"pop": "9",
			"corner": [
				1,
				1,
				1,
				1
			]
		},
		{
			"rank": 4,
			"waku": "枠4青",
			"umaban": 4,
			"horse": "エコロレイズ",
			"age": "牡3",
			"weight": "57.0",
			"jockey": "横山 和生",
			"time": "2:00.2",
			"margin": "クビ",
			"h_weight": 498,
			"h_weight_zougen": -8,
			"f_time": "34.8",
			"trainer": "岩戸 孝樹",
			"pop": "11",
			"corner": [
				7,
				7,
				7,
				7
			]
		},
		{
			"rank": 5,
			"waku": "枠3赤",
			"umaban": 3,
			"horse": "シュバルツクーゲル",
			"age": "牡3",
			"weight": "57.0",
			"jockey": "西村 淳也",
			"time": "2:00.5",
			"margin": "１ 3/4",
			"h_weight": 492,
			"h_weight_zougen": 18,
			"f_time": "35.6",
			"trainer": "鹿戸 雄一",
			"pop": "5",
			"corner": [
				2,
				2,
				2,
				3
			]
		},
		{
			"rank": 6,
			"waku": "枠6緑",
			"umaban": 6,
			"horse": "トロヴァトーレ",
			"age": "牡3",
			"weight": "57.0",
			"jockey": "C.ルメール",
			"time": "2:00.7",
			"margin": "１",
			"h_weight": 496,
			"h_weight_zougen": 6,
			"f_time": "35.5",
			"trainer": "鹿戸 雄一",
			"pop": "1",
			"corner": [
				5,
				5,
				5,
				6
			]
		},
		{
			"rank": 7,
			"waku": "枠7橙",
			"umaban": 9,
			"horse": "ダノンエアズロック",
			"age": "牡3",
			"weight": "57.0",
			"jockey": "R.キング",
			"time": "2:00.7",
			"margin": "ハナ",
			"h_weight": 504,
			"h_weight_zougen": 18,
			"f_time": "35.7",
			"trainer": "堀 宣行",
			"pop": "2",
			"corner": [
				3,
				3,
				4,
				3
			]
		},
		{
			"rank": 8,
			"waku": "枠1白",
			"umaban": 1,
			"horse": "アドミラルシップ",
			"age": "牡3",
			"weight": "57.0",
			"jockey": "戸崎 圭太",
			"time": "2:00.9",
			"margin": "１ 1/4",
			"h_weight": 460,
			"h_weight_zougen": 0,
			"f_time": "35.0",
			"trainer": "相沢 郁",
			"pop": "7",
			"corner": [
				11,
				11,
				10,
				9
			]
		},
		{
			"rank": 9,
			"waku": "枠8桃",
			"umaban": 10,
			"horse": "ファビュラススター",
			"age": "牡3",
			"weight": "57.0",
			"jockey": "横山 武史",
			"time": "2:01.0",
			"margin": "１／２",
			"h_weight": 502,
			"h_weight_zougen": 4,
			"f_time": "35.6",
			"trainer": "萩原 清",
			"pop": "4",
			"corner": [
				6,
				6,
				7,
				8
			]
		},
		{
			"rank": 10,
			"waku": "枠8桃",
			"umaban": 11,
			"horse": "ニシノフィアンス",
			"age": "牡3",
			"weight": "57.0",
			"jockey": "内田 博幸",
			"time": "2:01.4",
			"margin": "２ 1/2",
			"h_weight": 500,
			"h_weight_zougen": 2,
			"f_time": "35.7",
			"trainer": "竹内 正洋",
			"pop": "8",
			"corner": [
				7,
				7,
				9,
				10
			]
		},
		{
			"rank": 11,
			"waku": "枠2黒",
			"umaban": 2,
			"horse": "レッドテリオス",
			"age": "牡3",
			"weight": "57.0",
			"jockey": "津村 明秀",
			"time": "2:01.6",
			"margin": "１ 1/2",
			"h_weight": 466,
			"h_weight_zougen": 0,
			"f_time": "35.8",
			"trainer": "古賀 慎明",
			"pop": "10",
			"corner": [
				10,
				10,
				10,
				10
			]
		}
	]
}